[{"id":"bf8973c03f2ebd7e","type":"tab","label":"OurWeather Ingest","disabled":false,"info":"","env":[]},{"id":"b05d80ba4411e55b","type":"ha-entity","z":"bf8973c03f2ebd7e","name":"OutdoorTemperature","server":"aad44a62.80a0c","version":1,"debugenabled":false,"outputs":1,"entityType":"sensor","config":[{"property":"name","value":"OutdoorTemperature"},{"property":"device_class","value":"temperature"},{"property":"icon","value":""},{"property":"unit_of_measurement","value":"°F"}],"state":"payload.OutdoorTemperature","stateType":"msg","attributes":[],"resend":true,"outputLocation":"payload","outputLocationType":"none","inputOverride":"allow","outputOnStateChange":false,"outputPayload":"$entity().state ? \"on\": \"off\"","outputPayloadType":"jsonata","x":700,"y":260,"wires":[["a9ce2bdd4987c89e","c534b29daa5701d9"]]},{"id":"84e6343ed0e19277","type":"ha-entity","z":"bf8973c03f2ebd7e","name":"OutdoorHumidity","server":"aad44a62.80a0c","version":1,"debugenabled":false,"outputs":1,"entityType":"sensor","config":[{"property":"name","value":"OutdoorHumidity"},{"property":"device_class","value":"humidity"},{"property":"icon","value":""},{"property":"unit_of_measurement","value":"%"}],"state":"payload.variables.OutdoorHumidity","stateType":"msg","attributes":[],"resend":true,"outputLocation":"payload","outputLocationType":"none","inputOverride":"allow","outputOnStateChange":false,"outputPayload":"$entity().state ? \"on\": \"off\"","outputPayloadType":"jsonata","x":690,"y":320,"wires":[[]]},{"id":"5e9e8df8e2c1f0ab","type":"ha-entity","z":"bf8973c03f2ebd7e","name":"BarometricPressure","server":"aad44a62.80a0c","version":1,"debugenabled":false,"outputs":1,"entityType":"sensor","config":[{"property":"name","value":"BarometricPressure"},{"property":"device_class","value":"pressure"},{"property":"icon","value":""},{"property":"unit_of_measurement","value":"inches"}],"state":"payload.BarometricPressure","stateType":"msg","attributes":[],"resend":true,"outputLocation":"payload","outputLocationType":"none","inputOverride":"allow","outputOnStateChange":false,"outputPayload":"$entity().state ? \"on\": \"off\"","outputPayloadType":"jsonata","x":700,"y":140,"wires":[[]]},{"id":"b662ccf6be31662a","type":"ha-entity","z":"bf8973c03f2ebd7e","name":"IndoorTemperature","server":"aad44a62.80a0c","version":1,"debugenabled":false,"outputs":1,"entityType":"sensor","config":[{"property":"name","value":"IndoorTemperature"},{"property":"device_class","value":"temperature"},{"property":"icon","value":""},{"property":"unit_of_measurement","value":"°F"}],"state":"payload.IndoorTemperature","stateType":"msg","attributes":[],"resend":true,"outputLocation":"payload","outputLocationType":"none","inputOverride":"allow","outputOnStateChange":false,"outputPayload":"$entity().state ? \"on\": \"off\"","outputPayloadType":"jsonata","x":690,"y":80,"wires":[[]]},{"id":"062cf5cf4e2e9846","type":"ha-entity","z":"bf8973c03f2ebd7e","name":"CurrentWindDirection","server":"aad44a62.80a0c","version":1,"debugenabled":false,"outputs":1,"entityType":"sensor","config":[{"property":"name","value":"CurrentWindDirection"},{"property":"device_class","value":""},{"property":"icon","value":""},{"property":"unit_of_measurement","value":"°"}],"state":"payload.variables.CurrentWindDirection","stateType":"msg","attributes":[],"resend":true,"outputLocation":"payload","outputLocationType":"none","inputOverride":"allow","outputOnStateChange":false,"outputPayload":"$entity().state ? \"on\": \"off\"","outputPayloadType":"jsonata","x":700,"y":500,"wires":[[]]},{"id":"0b480ec3afa40c81","type":"ha-entity","z":"bf8973c03f2ebd7e","name":"WindSpeedMax","server":"aad44a62.80a0c","version":1,"debugenabled":false,"outputs":1,"entityType":"sensor","config":[{"property":"name","value":"WindSpeedMax"},{"property":"device_class","value":""},{"property":"icon","value":""},{"property":"unit_of_measurement","value":"mph"}],"state":"payload.WindSpeedMax","stateType":"msg","attributes":[],"resend":true,"outputLocation":"payload","outputLocationType":"none","inputOverride":"allow","outputOnStateChange":false,"outputPayload":"$entity().state ? \"on\": \"off\"","outputPayloadType":"jsonata","x":680,"y":740,"wires":[[]]},{"id":"af01960c16d202d5","type":"unit-converter","z":"bf8973c03f2ebd7e","category":"temperature","inputUnit":"C","outputUnit":"F","inputField":"payload.variables.OutdoorTemperature","outputField":"payload.OutdoorTemperature","inputFieldType":"msg","outputFieldType":"msg","roundOutputField":true,"outputFieldDecimals":"1","name":"OT CtoF","x":480,"y":260,"wires":[["b05d80ba4411e55b"]]},{"id":"e6ed09691d7d177b","type":"unit-converter","z":"bf8973c03f2ebd7e","category":"temperature","inputUnit":"C","outputUnit":"F","inputField":"payload.variables.IndoorTemperature","outputField":"payload.IndoorTemperature","inputFieldType":"msg","outputFieldType":"msg","roundOutputField":true,"outputFieldDecimals":"1","name":"IT CtoF","x":480,"y":80,"wires":[["b662ccf6be31662a"]]},{"id":"6f514f53a5134a5e","type":"unit-converter","z":"bf8973c03f2ebd7e","category":"speed","inputUnit":"km/h","outputUnit":"m/h","inputField":"payload.variables.WindSpeedMax","outputField":"payload.WindSpeedMax","inputFieldType":"msg","outputFieldType":"msg","roundOutputField":true,"outputFieldDecimals":"1","name":"WSMax KtoM","x":500,"y":740,"wires":[["0b480ec3afa40c81"]]},{"id":"8621a4bf137bb237","type":"unit-converter","z":"bf8973c03f2ebd7e","category":"speed","inputUnit":"km/h","outputUnit":"m/h","inputField":"payload.variables.WindGustMax","outputField":"payload.WindGustMax","inputFieldType":"msg","outputFieldType":"msg","roundOutputField":true,"outputFieldDecimals":"1","name":"WGMax KtoM","x":500,"y":800,"wires":[["438efda23e9a7dc6"]]},{"id":"52075a72461b703f","type":"unit-converter","z":"bf8973c03f2ebd7e","category":"length","inputUnit":"mm","outputUnit":"in","inputField":"payload.variables.RainCalendarDay","outputField":"payload.RainCalendarDayInches","inputFieldType":"msg","outputFieldType":"msg","roundOutputField":true,"outputFieldDecimals":"2","name":"RainDaymmtoIn","x":500,"y":1280,"wires":[["a2ae110ef83f6a56"]]},{"id":"1489313220f99a61","type":"unit-converter","z":"bf8973c03f2ebd7e","category":"length","inputUnit":"mm","outputUnit":"in","inputField":"payload.variables.Rain60Minutes","outputField":"payload.Rain60MinutesInches","inputFieldType":"msg","outputFieldType":"msg","roundOutputField":true,"outputFieldDecimals":"2","name":"Rain60mmtoIn","x":500,"y":1220,"wires":[["12cad7c37c2d7661"]]},{"id":"7aac79a95a7bd898","type":"http request","z":"bf8973c03f2ebd7e","name":"GET-Weather-API","method":"GET","ret":"obj","paytoqs":"body","url":"http://172.16.3.128","tls":"","persist":false,"proxy":"","authType":"","senderr":false,"x":230,"y":620,"wires":[["af01960c16d202d5","e6ed09691d7d177b","84e6343ed0e19277","062cf5cf4e2e9846","6f514f53a5134a5e","8621a4bf137bb237","1489313220f99a61","52075a72461b703f","019217ec0669d4a3","bec620b153f34c0d","873d39151cdb04ca","90680fe6749b1446","afc631120b88180e","bdd9cfd608d863e9","3d4206d113d0e17f","eed4d583be0ad194","b3e563f947910377","8e7e934e233dcae7","41a26eda9ef6250b","e249de8d7d90ac74","810f570c71bcb85c"]]},{"id":"3a93c1f5f9040d1e","type":"inject","z":"bf8973c03f2ebd7e","name":"Start","props":[{"p":"payload"},{"p":"topic","vt":"str"}],"repeat":"5","crontab":"","once":true,"onceDelay":0.1,"topic":"","payloadType":"date","x":70,"y":620,"wires":[["7aac79a95a7bd898"]]},{"id":"438efda23e9a7dc6","type":"ha-entity","z":"bf8973c03f2ebd7e","name":"WindGustMax","server":"aad44a62.80a0c","version":1,"debugenabled":false,"outputs":1,"entityType":"sensor","config":[{"property":"name","value":"WindGustMax"},{"property":"device_class","value":""},{"property":"icon","value":""},{"property":"unit_of_measurement","value":"mph"}],"state":"payload.WindGustMax","stateType":"msg","attributes":[],"resend":true,"outputLocation":"payload","outputLocationType":"none","inputOverride":"allow","outputOnStateChange":false,"outputPayload":"$entity().state ? \"on\": \"off\"","outputPayloadType":"jsonata","x":680,"y":800,"wires":[[]]},{"id":"019217ec0669d4a3","type":"function","z":"bf8973c03f2ebd7e","name":"BP BartoInHg","func":"var x = msg.payload.variables.BarometricPressure\nmsg.payload.BarometricPressure = (x / 3386).toFixed(2);\nreturn msg;","outputs":1,"noerr":0,"initialize":"","finalize":"","libs":[],"x":500,"y":140,"wires":[["5e9e8df8e2c1f0ab"]]},{"id":"a2ae110ef83f6a56","type":"ha-entity","z":"bf8973c03f2ebd7e","name":"RainCalendarDay","server":"aad44a62.80a0c","version":1,"debugenabled":false,"outputs":1,"entityType":"sensor","config":[{"property":"name","value":"RainCalendarDay"},{"property":"device_class","value":""},{"property":"icon","value":""},{"property":"unit_of_measurement","value":"in"}],"state":"payload.RainCalendarDayInches","stateType":"msg","attributes":[],"resend":true,"outputLocation":"payload","outputLocationType":"none","inputOverride":"allow","outputOnStateChange":false,"outputPayload":"$entity().state ? \"on\": \"off\"","outputPayloadType":"jsonata","x":690,"y":1280,"wires":[[]]},{"id":"12cad7c37c2d7661","type":"ha-entity","z":"bf8973c03f2ebd7e","name":"Rain60Minutes","server":"aad44a62.80a0c","version":1,"debugenabled":false,"outputs":1,"entityType":"sensor","config":[{"property":"name","value":"Rain60Minutes"},{"property":"device_class","value":""},{"property":"icon","value":""},{"property":"unit_of_measurement","value":"in"}],"state":"payload.Rain60MinutesInches","stateType":"msg","attributes":[],"resend":true,"outputLocation":"payload","outputLocationType":"none","inputOverride":"allow","outputOnStateChange":false,"outputPayload":"$entity().state ? \"on\": \"off\"","outputPayloadType":"jsonata","x":680,"y":1220,"wires":[[]]},{"id":"a9ce2bdd4987c89e","type":"smooth","z":"bf8973c03f2ebd7e","name":"minOutTemp","property":"payload.OutsideTemperatureF","action":"min","count":"17280","round":"","mult":"single","reduce":false,"x":910,"y":240,"wires":[[]]},{"id":"c534b29daa5701d9","type":"smooth","z":"bf8973c03f2ebd7e","name":"maxOutTemp","property":"payload.OutsideTemperatureF","action":"max","count":"17280","round":"","mult":"single","reduce":false,"x":910,"y":280,"wires":[[]]},{"id":"b2811876b6c4d05c","type":"ha-entity","z":"bf8973c03f2ebd7e","name":"Altitude","server":"aad44a62.80a0c","version":1,"debugenabled":false,"outputs":1,"entityType":"sensor","config":[{"property":"name","value":"Altitude"},{"property":"device_class","value":""},{"property":"icon","value":""},{"property":"unit_of_measurement","value":"feet"}],"state":"payload.Altitude","stateType":"msg","attributes":[],"resend":true,"outputLocation":"payload","outputLocationType":"none","inputOverride":"allow","outputOnStateChange":false,"outputPayload":"$entity().state ? \"on\": \"off\"","outputPayloadType":"jsonata","x":660,"y":200,"wires":[[]]},{"id":"bec620b153f34c0d","type":"unit-converter","z":"bf8973c03f2ebd7e","category":"length","inputUnit":"m","outputUnit":"ft","inputField":"payload.variables.Altitude","outputField":"payload.Altitude","inputFieldType":"msg","outputFieldType":"msg","roundOutputField":true,"outputFieldDecimals":"1","name":"Alt MtoF","x":480,"y":200,"wires":[["b2811876b6c4d05c"]]},{"id":"a067ad10049c9b2d","type":"ha-entity","z":"bf8973c03f2ebd7e","name":"CurrentWindSpeed","server":"aad44a62.80a0c","version":1,"debugenabled":false,"outputs":1,"entityType":"sensor","config":[{"property":"name","value":"CurrentWindSpeed"},{"property":"device_class","value":""},{"property":"icon","value":""},{"property":"unit_of_measurement","value":"mph"}],"state":"payload.CurrentWindSpeed","stateType":"msg","attributes":[],"resend":true,"outputLocation":"payload","outputLocationType":"none","inputOverride":"allow","outputOnStateChange":false,"outputPayload":"$entity().state ? \"on\": \"off\"","outputPayloadType":"jsonata","x":690,"y":380,"wires":[[]]},{"id":"873d39151cdb04ca","type":"unit-converter","z":"bf8973c03f2ebd7e","category":"speed","inputUnit":"km/h","outputUnit":"m/h","inputField":"payload.variables.CurrentWindSpeed","outputField":"payload.CurrentWindSpeed","inputFieldType":"msg","outputFieldType":"msg","roundOutputField":true,"outputFieldDecimals":"1","name":"CWS KtoM","x":490,"y":380,"wires":[["a067ad10049c9b2d"]]},{"id":"90680fe6749b1446","type":"unit-converter","z":"bf8973c03f2ebd7e","category":"speed","inputUnit":"km/h","outputUnit":"m/h","inputField":"payload.variables.CurrentWindGust","outputField":"payload.CurrentWindGust","inputFieldType":"msg","outputFieldType":"msg","roundOutputField":true,"outputFieldDecimals":"1","name":"CWG KtoM","x":490,"y":440,"wires":[["d14fed0eb0178e11"]]},{"id":"d14fed0eb0178e11","type":"ha-entity","z":"bf8973c03f2ebd7e","name":"CurrentWindGust","server":"aad44a62.80a0c","version":1,"debugenabled":false,"outputs":1,"entityType":"sensor","config":[{"property":"name","value":"CurrentWindGust"},{"property":"device_class","value":""},{"property":"icon","value":""},{"property":"unit_of_measurement","value":"mph"}],"state":"payload.CurrentWindGust","stateType":"msg","attributes":[],"resend":true,"outputLocation":"payload","outputLocationType":"none","inputOverride":"allow","outputOnStateChange":false,"outputPayload":"$entity().state ? \"on\": \"off\"","outputPayloadType":"jsonata","x":690,"y":440,"wires":[[]]},{"id":"afc631120b88180e","type":"ha-entity","z":"bf8973c03f2ebd7e","name":"EnglishOrMetric","server":"aad44a62.80a0c","version":1,"debugenabled":false,"outputs":1,"entityType":"binary_sensor","config":[{"property":"name","value":"EnglishOrMetric"},{"property":"device_class","value":""},{"property":"icon","value":""},{"property":"unit_of_measurement","value":"°"}],"state":"payload.variables.EnglishOrMetric","stateType":"msg","attributes":[],"resend":true,"outputLocation":"payload","outputLocationType":"none","inputOverride":"allow","outputOnStateChange":false,"outputPayload":"$entity().state ? \"on\": \"off\"","outputPayloadType":"jsonata","x":680,"y":560,"wires":[[]]},{"id":"bdd9cfd608d863e9","type":"unit-converter","z":"bf8973c03f2ebd7e","category":"length","inputUnit":"mm","outputUnit":"in","inputField":"payload.variables.RainTotal","outputField":"payload.RainTotal","inputFieldType":"msg","outputFieldType":"msg","roundOutputField":true,"outputFieldDecimals":"2","name":"RT mmtoIn","x":490,"y":620,"wires":[["763cd83fdfdc9cb0"]]},{"id":"763cd83fdfdc9cb0","type":"ha-entity","z":"bf8973c03f2ebd7e","name":"RainTotal","server":"aad44a62.80a0c","version":1,"debugenabled":false,"outputs":1,"entityType":"sensor","config":[{"property":"name","value":"RainTotal"},{"property":"device_class","value":""},{"property":"icon","value":""},{"property":"unit_of_measurement","value":"in"}],"state":"payload.RainTotal","stateType":"msg","attributes":[],"resend":true,"outputLocation":"payload","outputLocationType":"none","inputOverride":"allow","outputOnStateChange":false,"outputPayload":"$entity().state ? \"on\": \"off\"","outputPayloadType":"jsonata","x":660,"y":620,"wires":[[]]},{"id":"470033fd3b01e8a1","type":"ha-entity","z":"bf8973c03f2ebd7e","name":"WindSpeedMin","server":"aad44a62.80a0c","version":1,"debugenabled":false,"outputs":1,"entityType":"sensor","config":[{"property":"name","value":"WindSpeedMin"},{"property":"device_class","value":""},{"property":"icon","value":""},{"property":"unit_of_measurement","value":"mph"}],"state":"payload.WindSpeedMin","stateType":"msg","attributes":[],"resend":true,"outputLocation":"payload","outputLocationType":"none","inputOverride":"allow","outputOnStateChange":false,"outputPayload":"$entity().state ? \"on\": \"off\"","outputPayloadType":"jsonata","x":680,"y":680,"wires":[[]]},{"id":"3d4206d113d0e17f","type":"unit-converter","z":"bf8973c03f2ebd7e","category":"speed","inputUnit":"km/h","outputUnit":"m/h","inputField":"payload.variables.WindSpeedMin","outputField":"payload.WindSpeedMin","inputFieldType":"msg","outputFieldType":"msg","roundOutputField":true,"outputFieldDecimals":"1","name":"WSMin KtoM","x":490,"y":680,"wires":[["470033fd3b01e8a1"]]},{"id":"eed4d583be0ad194","type":"unit-converter","z":"bf8973c03f2ebd7e","category":"speed","inputUnit":"km/h","outputUnit":"m/h","inputField":"payload.variables.WindGustMin","outputField":"payload.WindGustMin","inputFieldType":"msg","outputFieldType":"msg","roundOutputField":true,"outputFieldDecimals":"1","name":"WGMin KtoM","x":490,"y":860,"wires":[["1f177d609e073e9f"]]},{"id":"1f177d609e073e9f","type":"ha-entity","z":"bf8973c03f2ebd7e","name":"WindGustMin","server":"aad44a62.80a0c","version":1,"debugenabled":false,"outputs":1,"entityType":"sensor","config":[{"property":"name","value":"WindGustMin"},{"property":"device_class","value":""},{"property":"icon","value":""},{"property":"unit_of_measurement","value":"mph"}],"state":"payload.WindGustMin","stateType":"msg","attributes":[],"resend":true,"outputLocation":"payload","outputLocationType":"none","inputOverride":"allow","outputOnStateChange":false,"outputPayload":"$entity().state ? \"on\": \"off\"","outputPayloadType":"jsonata","x":680,"y":860,"wires":[[]]},{"id":"b3e563f947910377","type":"ha-entity","z":"bf8973c03f2ebd7e","name":"WindDirectionMin","server":"aad44a62.80a0c","version":1,"debugenabled":false,"outputs":1,"entityType":"sensor","config":[{"property":"name","value":"WindDirectionMin"},{"property":"device_class","value":""},{"property":"icon","value":""},{"property":"unit_of_measurement","value":"°"}],"state":"payload.variables.WindDirectionMin","stateType":"msg","attributes":[],"resend":true,"outputLocation":"payload","outputLocationType":"none","inputOverride":"allow","outputOnStateChange":false,"outputPayload":"$entity().state ? \"on\": \"off\"","outputPayloadType":"jsonata","x":690,"y":920,"wires":[[]]},{"id":"8e7e934e233dcae7","type":"ha-entity","z":"bf8973c03f2ebd7e","name":"WindDirectionMax","server":"aad44a62.80a0c","version":1,"debugenabled":false,"outputs":1,"entityType":"sensor","config":[{"property":"name","value":"WindDirectionMax"},{"property":"device_class","value":""},{"property":"icon","value":""},{"property":"unit_of_measurement","value":"°"}],"state":"payload.variables.WindDirectionMax","stateType":"msg","attributes":[],"resend":true,"outputLocation":"payload","outputLocationType":"none","inputOverride":"allow","outputOnStateChange":false,"outputPayload":"$entity().state ? \"on\": \"off\"","outputPayloadType":"jsonata","x":690,"y":980,"wires":[[]]},{"id":"41a26eda9ef6250b","type":"ha-entity","z":"bf8973c03f2ebd7e","name":"AirQualitySensor","server":"aad44a62.80a0c","version":1,"debugenabled":false,"outputs":1,"entityType":"sensor","config":[{"property":"name","value":"AirQualitySensor"},{"property":"device_class","value":""},{"property":"icon","value":""},{"property":"unit_of_measurement","value":""}],"state":"payload.variables.AirQualitySensor","stateType":"msg","attributes":[],"resend":true,"outputLocation":"payload","outputLocationType":"none","inputOverride":"allow","outputOnStateChange":false,"outputPayload":"$entity().state ? \"on\": \"off\"","outputPayloadType":"jsonata","x":690,"y":1040,"wires":[[]]},{"id":"e249de8d7d90ac74","type":"ha-entity","z":"bf8973c03f2ebd7e","name":"ThunderBoardLast","server":"aad44a62.80a0c","version":1,"debugenabled":false,"outputs":1,"entityType":"sensor","config":[{"property":"name","value":"ThunderBoardLast"},{"property":"device_class","value":""},{"property":"icon","value":""},{"property":"unit_of_measurement","value":""}],"state":"payload.variables.ThunderBoardLast","stateType":"msg","attributes":[],"resend":true,"outputLocation":"payload","outputLocationType":"none","inputOverride":"allow","outputOnStateChange":false,"outputPayload":"$entity().state ? \"on\": \"off\"","outputPayloadType":"jsonata","x":690,"y":1100,"wires":[[]]},{"id":"810f570c71bcb85c","type":"ha-entity","z":"bf8973c03f2ebd7e","name":"ThunderBoardParams","server":"aad44a62.80a0c","version":1,"debugenabled":false,"outputs":1,"entityType":"sensor","config":[{"property":"name","value":"ThunderBoardParams"},{"property":"device_class","value":""},{"property":"icon","value":""},{"property":"unit_of_measurement","value":""}],"state":"payload.variables.ThunderBoardParams","stateType":"msg","attributes":[],"resend":true,"outputLocation":"payload","outputLocationType":"none","inputOverride":"allow","outputOnStateChange":false,"outputPayload":"$entity().state ? \"on\": \"off\"","outputPayloadType":"jsonata","x":700,"y":1160,"wires":[[]]},{"id":"aad44a62.80a0c","type":"server","name":"Home Assistant","version":2,"addon":true,"rejectUnauthorizedCerts":true,"ha_boolean":"y|yes|true|on|home|open","connectionDelay":true,"cacheJson":true,"heartbeat":false,"heartbeatInterval":30}]